[{"model": "ems.form_config", "pk": 1, "fields": {"form": 1, "col_name": "confirm", "col_type": "label", "options": "", "hint": "", "label": "Click on SAVE to confirm event", "constraints": "", "required": "1", "order": 0, "page": 0}}, {"model": "ems.form_config", "pk": 7, "fields": {"form": 3, "col_name": "cancel", "col_type": "label", "options": "Click on save to DISCARD this event", "hint": "", "label": "Click on save to DISCARD this event", "constraints": "", "required": "0", "order": 0, "page": 0}}, {"model": "ems.form_config", "pk": 8, "fields": {"form": 4, "col_name": "source_of_events", "col_type": "textarea", "options": "", "hint": "", "label": "Source of events and overall situation to date", "constraints": "", "required": "1", "order": 1, "page": 0}}, {"model": "ems.form_config", "pk": 9, "fields": {"form": 4, "col_name": "general_impact", "col_type": "textarea", "options": "", "hint": "", "label": "General Impact", "constraints": "", "required": "1", "order": 2, "page": 0}}, {"model": "ems.form_config", "pk": 10, "fields": {"form": 2, "col_name": "label", "col_type": "label", "options": "", "hint": "", "label": "Please provide information of what kind of information you require", "constraints": "", "required": "0", "order": 0, "page": 0}}, {"model": "ems.form_config", "pk": 11, "fields": {"form": 2, "col_name": "Remarks", "col_type": "textarea", "options": "", "hint": "", "label": "", "constraints": "", "required": "0", "order": 0, "page": 0}}, {"model": "ems.form_config", "pk": 12, "fields": {"form": 5, "col_name": "validity", "col_type": "radio", "options": "True, False", "hint": "Did this event occur", "label": "Validity of the Event", "constraints": "", "required": "1", "order": 0, "page": 0}}, {"model": "ems.form_config", "pk": 13, "fields": {"form": 5, "col_name": "severity", "col_type": "select1", "options": "Low, Moderate,High,Very High", "hint": "", "label": "Severity", "constraints": "", "required": "1", "order": 1, "page": 0}}, {"model": "ems.form_config", "pk": 14, "fields": {"form": 5, "col_name": "description", "col_type": "textarea", "options": "", "hint": "Please provide description of the event", "label": "Description", "constraints": "", "required": "1", "order": 0, "page": 0}}, {"model": "ems.form_config", "pk": 15, "fields": {"form": 6, "col_name": "closed", "col_type": "label", "options": "", "hint": "", "label": "Press SAVE to CLOSE event", "constraints": "", "required": "0", "order": 0, "page": 0}}, {"model": "ems.form_config", "pk": 16, "fields": {"form": 1, "col_name": "upload", "col_type": "upload", "options": "", "hint": "Please select file to upload", "label": "", "constraints": "", "required": "0", "order": 0, "page": 0}}, {"model": "ems.form_config", "pk": 17, "fields": {"form": 1, "col_name": "upload2", "col_type": "upload", "options": "", "hint": "some hint here", "label": "another upload", "constraints": "", "required": "0", "order": 0, "page": 0}}]